trendln/__init__.py
trendln2-2.0.25.dist-info/licenses/LICENSE
trendln2-2.0.25.dist-info/METADATA
trendln2-2.0.25.dist-info/WHEEL
trendln2-2.0.25.dist-info/top_level.txt
trendln2-2.0.25.dist-info/RECORD
