Metadata-Version: 2.4
Name: trendln2
Version: 2.0.25
Summary: Support and Resistance Trend lines Calculator for Financial Analysis
Home-page: https://github.com/ShriekinNinja/trendln
Author: Gregory Morse
Author-email: gregory.morse@live.com
License: MIT
Keywords: trendlines,trend lines,trend,support,resistance,trends,technical,indicators,financial,analysis
Platform: any
Classifier: License :: OSI Approved :: MIT License
Classifier: Development Status :: 5 - Production/Stable
Classifier: Operating System :: OS Independent
Classifier: Intended Audience :: Developers
Classifier: Topic :: Office/Business :: Financial
Classifier: Topic :: Office/Business :: Financial :: Investment
Classifier: Topic :: Software Development :: Libraries
Classifier: Topic :: Software Development :: Libraries :: Python Modules
Classifier: Programming Language :: Python :: 3.13
License-File: LICENSE
Requires-Dist: numpy>=2.3.5
Requires-Dist: findiff>=0.12.1
Requires-Dist: scikit-image>=0.25.2
Requires-Dist: pandas>=2.3.3
Requires-Dist: matplotlib>=3.10.7
Dynamic: author
Dynamic: author-email
Dynamic: classifier
Dynamic: description
Dynamic: description-content-type
Dynamic: home-page
Dynamic: keywords
Dynamic: license
Dynamic: license-file
Dynamic: platform
Dynamic: requires-dist
Dynamic: summary
